[{"sources": [], "region": "African Region", "countries": [{"source": null, "score": null, "name": "Angola"}, {"source": null, "score": null, "name": "Benin"}, {"source": null, "score": 5269.770982, "name": "Botswana"}, {"source": null, "score": 621, "name": "Burkina Faso"}, {"source": null, "score": null, "name": "Burundi"}, {"source": null, "score": null, "name": "Cameroon"}, {"source": null, "score": null, "name": "Central African Republic"}, {"source": null, "score": null, "name": "Chad"}, {"source": null, "score": null, "name": "Comoros"}, {"source": null, "score": null, "name": "Congo"}, {"source": null, "score": 1364, "name": "C\u00f4te d'Ivoire"}, {"source": null, "score": 1074, "name": "Democratic Republic of the Congo"}, {"source": null, "score": null, "name": "Equatorial Guinea"}, {"source": null, "score": null, "name": "Eritrea"}, {"source": null, "score": 1116, "name": "Ethiopia"}, {"source": null, "score": null, "name": "Gabon"}, {"source": null, "score": null, "name": "Gambia"}, {"source": null, "score": 1074, "name": "Ghana"}, {"source": null, "score": null, "name": "Guinea"}, {"source": null, "score": null, "name": "Guinea-Bissau"}, {"source": null, "score": 1607.3691813175922, "name": "Kenya"}, {"source": null, "score": null, "name": "Lesotho"}, {"source": null, "score": 101, "name": "Liberia"}, {"source": null, "score": null, "name": "Madagascar"}, {"source": null, "score": null, "name": "Malawi"}, {"source": null, "score": null, "name": "Mali"}, {"source": null, "score": 156, "name": "Mauritania"}, {"source": null, "score": null, "name": "Mozambique"}, {"source": null, "score": 285, "name": "Niger"}, {"source": null, "score": null, "name": "Nigeria"}, {"source": null, "score": null, "name": "Rwanda"}, {"source": null, "score": null, "name": "Sao Tome and Principe"}, {"source": null, "score": null, "name": "Senegal"}, {"source": null, "score": null, "name": "Sierra Leone"}, {"source": null, "score": null, "name": "South Africa"}, {"source": null, "score": null, "name": "Swaziland"}, {"source": null, "score": null, "name": "Togo"}, {"source": null, "score": 1074, "name": "Uganda"}, {"source": null, "score": 1074, "name": "United Republic of Tanzania"}, {"source": null, "score": null, "name": "Zambia"}, {"source": null, "score": null, "name": "Zimbabwe"}], "indicator": "4.1", "target": "Y"}]